xu_34983_add_mcp_demo/__init__.py
xu_34983_add_mcp_demo-0.1.0.dist-info/WHEEL
xu_34983_add_mcp_demo-0.1.0.dist-info/entry_points.txt
xu_34983_add_mcp_demo-0.1.0.dist-info/METADATA
xu_34983_add_mcp_demo-0.1.0.dist-info/RECORD
