Metadata-Version: 2.3
Name: xu-34983-add-mcp-demo
Version: 0.1.0
Summary: Add your description here
Author: GuoqingXu21
Author-email: GuoqingXu21 <guoqingxu26@gmail.com>
Requires-Dist: mcp[cli]>=1.25.0
Requires-Python: >=3.10.4
